xybase/__init__.py
xybase/converter.py
xybase/email.py
xybase/files.py
xybase/reflection.py
xybase-0.0.1.dist-info/LICENSE
xybase-0.0.1.dist-info/METADATA
xybase-0.0.1.dist-info/WHEEL
xybase-0.0.1.dist-info/top_level.txt
xybase-0.0.1.dist-info/RECORD
